py_qj_robots/__init__.py
py_qj_robots/authorization.py
py_qj_robots/perception.py
py_qj_robots-0.1.13.dist-info/licenses/LICENSE
py_qj_robots-0.1.13.dist-info/METADATA
py_qj_robots-0.1.13.dist-info/WHEEL
py_qj_robots-0.1.13.dist-info/top_level.txt
py_qj_robots-0.1.13.dist-info/RECORD
