Metadata-Version: 2.4
Name: py-qj-robots
Version: 0.1.13
Summary: QJ Python SDK
Home-page: https://github.com/QJ-ROBOTS/perception-python-sdk
Author: QJ ROBOTS
Author-email: github@qj-robots.com
Classifier: Programming Language :: Python :: 3
Classifier: License :: OSI Approved :: MIT License
Classifier: Operating System :: OS Independent
Requires-Python: >=3.0
License-File: LICENSE
Requires-Dist: requests>=2.26.0
Requires-Dist: python-dotenv>=0.19.0
Dynamic: author
Dynamic: author-email
Dynamic: classifier
Dynamic: description
Dynamic: description-content-type
Dynamic: home-page
Dynamic: license-file
Dynamic: requires-dist
Dynamic: requires-python
Dynamic: summary
